core/setup.py
core/external/fmt/CONTRIBUTING.md
core/external/fmt/.github/issue_template.md
core/external/fmt/.github/pull_request_template.md
core/external/fmt/doc/build.py
core/external/fmt/doc/conf.py
core/external/fmt/support/build-docs.py
core/external/fmt/support/compute-powers.py
core/external/fmt/support/docopt.py
core/external/fmt/support/manage.py
core/external/fmt/support/printable.py
core/external/fmt/support/rst2md.py
core/external/fmt/support/bazel/README.md
core/external/fmt/support/rtd/conf.py
core/external/fmt/test/fuzzing/README.md
core/external/pybind11/SECURITY.md
core/external/pybind11/noxfile.py
core/external/pybind11/setup.py
core/external/pybind11/.github/CONTRIBUTING.md
core/external/pybind11/.github/pull_request_template.md
core/external/pybind11/docs/benchmark.py
core/external/pybind11/docs/conf.py
core/external/pybind11/pybind11/__init__.py
core/external/pybind11/pybind11/__main__.py
core/external/pybind11/pybind11/_version.py
core/external/pybind11/pybind11/commands.py
core/external/pybind11/pybind11/py.typed
core/external/pybind11/pybind11/setup_helpers.py
core/external/pybind11/tests/conftest.py
core/external/pybind11/tests/env.py
core/external/pybind11/tests/test_async.py
core/external/pybind11/tests/test_buffers.py
core/external/pybind11/tests/test_builtin_casters.py
core/external/pybind11/tests/test_call_policies.py
core/external/pybind11/tests/test_callbacks.py
core/external/pybind11/tests/test_chrono.py
core/external/pybind11/tests/test_class.py
core/external/pybind11/tests/test_const_name.py
core/external/pybind11/tests/test_constants_and_functions.py
core/external/pybind11/tests/test_copy_move.py
core/external/pybind11/tests/test_cpp_conduit.py
core/external/pybind11/tests/test_custom_type_casters.py
core/external/pybind11/tests/test_custom_type_setup.py
core/external/pybind11/tests/test_docstring_options.py
core/external/pybind11/tests/test_eigen_matrix.py
core/external/pybind11/tests/test_eigen_tensor.py
opengate-10.0.3.dist-info/licenses/AUTHORS
opengate-10.0.3.dist-info/licenses/LICENSE.md
opengate-10.0.3.dist-info/METADATA
opengate-10.0.3.dist-info/WHEEL
opengate-10.0.3.dist-info/entry_points.txt
opengate-10.0.3.dist-info/top_level.txt
opengate-10.0.3.dist-info/RECORD
