Metadata-Version: 2.4
Name: opengate
Version: 10.0.3
Summary: Simulation for Medical Physics
Author-email: Opengate collaboration <david.sarrut@creatis.insa-lyon.fr>
License:                    GNU LESSER GENERAL PUBLIC LICENSE
Classifier: Programming Language :: Python
Classifier: Programming Language :: Python :: 3.9
Classifier: Programming Language :: Python :: 3.10
Classifier: Programming Language :: Python :: 3.11
Classifier: Programming Language :: Python :: 3.12
Classifier: Programming Language :: Python :: Implementation :: PyPy
Classifier: Operating System :: OS Independent
Requires-Python: >=3.9
License-File: LICENSE.md
License-File: AUTHORS
Requires-Dist: colored>1.5
Requires-Dist: opengate-core==10.0.3
Requires-Dist: gatetools
Requires-Dist: click
Requires-Dist: python-box<7.0.0
Requires-Dist: anytree
Requires-Dist: numpy
Requires-Dist: itk
Requires-Dist: uproot
Requires-Dist: scipy
Requires-Dist: matplotlib
Requires-Dist: GitPython
Requires-Dist: meshio
Requires-Dist: radioactivedecay
Requires-Dist: jsonpickle
Requires-Dist: pandas
Requires-Dist: awkward-pandas
Requires-Dist: tables
Requires-Dist: requests
Requires-Dist: PyYAML
Requires-Dist: SimpleITK
Requires-Dist: spekpy
Requires-Dist: icrp107-database
Requires-Dist: loguru
Provides-Extra: novis
Requires-Dist: opengate-core-novis; extra == "novis"
Dynamic: license-file
Dynamic: requires-dist
